Workbook

Sheet ReadMe
A1: LOAN DEFAULT RISK | PROJECT OVERVIEW
A4: This capstone turns a public loan default dataset into an Excel demonstration of credit risk assessment. After checking the data with SQL, a logistic regression model was fitted in R and its coefficients were brought into this workbook. Enter an applicant profile to see an estimated default probability, a risk category, and a decision prompt with supporting indicators.
A8: HOW TO USE THE WORKBOOK
A9: 1 Enter the applicant details on Input. 2 Review the probability, classification, decision, and risk indicators on Results Dashboard. 3 Coefficients and Calculations contain the model inputs and scoring logic.
A12: WHAT THE MODEL DOES
A13: The workbook combines demographic, employment, loan, and financial fields—including credit score—using logistic regression coefficients. The score is translated into an estimated probability of default. The dashboard displays risk tiers below 5%, 5% to below 15%, 15% to below 25%, and 25% or higher; these cutoffs are demonstration choices, not validated lending policy.
A17: IMPORTANT CONTEXT
A18: This is an academic analytics portfolio project using the public Loan Default dataset. The notes report similar default rates in the training and test samples; they do not establish that the model is accurate or suitable for real borrowers. Do not use this workbook to approve, deny, or price real loans.
A23: METHOD · SQL data checks → R logistic regression → Excel input, score, and dashboard

Sheet Input
A1: LOAN APPLICATION INPUT
A3: Personal Information
A4: Age | B4: 45
A5: Annual Income | B5: 95000
A6: Months Employed | B6: 48
A7: Education Level | B7: Bachelor's
A8: Employment Type | B8: Full-Time
A9: Marital Status | B9: Divorced
A10: Has Dependents | B10: Yes
A12: Loan Details
A13: Loan Amount | B13: 85000
A14: Interest Rate (%) | B14: 15
A15: Loan Term (months) | B15: 36
A16: Loan Purpose | B16: Auto
A18: Financial Information
A19: Credit Score | B19: 750
A20: DTI Ratio (%) | B20: 0.6
A21: Number of Credit Lines | B21: 6
A22: Has Mortgage | B22: Yes
A23: Has Co-Signer | B23: Yes

Sheet Results Dashboard
A1: LOAN DEFAULT RISK ASSESSMENT
A2: Applicant: | C2: Date: | D2: =TODAY() -> 46308
A4: PREDICTION RESULTS
A5: Default Probability | B5: =Calculations!G8/100 -> 0.060849865
A6: Risk Classification | B6: =Calculations!G11 -> MEDIUM
A7: Confidence Level | B7: =IF(B5<0.05,"Very High",IF(B5<0.15,"High",IF(B5<0.25,"Medium","Low"))) -> High
A9: RECOMMENDATION
A10: Decision | B10: =IF(B6="LOW","✅ APPROVE",IF(B6="MEDIUM","⚠️ MANUAL REVIEW",IF(B6="HIGH","⚠️ CONDITIONAL APPROVAL","❌ DECLINE"))) -> ⚠️ MANUAL REVIEW
A12: DETAILED RISK ANALYSIS
A13: Primary Risk Factors
A14: Credit Score | B14: =IF(Input!B19<600,"🔴 Very Poor ("&Input!B19&")",IF(Input!B19<650,"🟡 Poor ("&Input!B19&")",IF(Input!B19<700,"🟢 Fair ("&Input!B19&")","✅ Good ("&Input!B19&")"))) -> ✅ Good (750)
A15: DTI Ratio | B15: =IF(Input!B20>0.4,"🔴 Very High ("&Input!B20&"%)",IF(Input!B20>0.35,"🟡 High ("&Input!B20&"%)",IF(Input!B20>0.25,"🟢 Moderate ("&Input!B20&"%)","✅ Low ("&Input!B20&"%)"))) -> 🔴 Very High (0.6%)
A16: Employment History | B16: =IF(Input!B6<6,"🔴 Very Short ("&Input!B6&" months)",IF(Input!B6<12,"🟡 Short ("&Input!B6&" months)",IF(Input!B6<24,"🟢 Moderate ("&Input!B6&" months)","✅ Stable ("&Input!B6&" months)"))) -> ✅ Stable (48 months)
A17: Loan-to-Income | B17: =IF((Input!B13/Input!B5)>5,"🔴 Very High ("&ROUND((Input!B13/Input!B5),2)&")",IF((Input!B13/Input!B5)>3,"🟡 High ("&ROUND((Input!B13/Input!B5),2)&")",IF((Input!B13/Input!B5)>1.5,"🟢 Moderate ("&ROUND((Input!B13/Input!B5),2)&")","✅ Conservative ("&ROUND((Input!B13/Input!B5),2)&")"))) -> ✅ Conservative (0.89)
A19: RISK MITIGATION FACTORS
A20: Co-Signer | B20: =IF(Input!B23="Yes","✅ Has Co-Signer (Risk Reduced)","⚠️ No Co-Signer") -> ✅ Has Co-Signer (Risk Reduced)
A21: Collateral | B21: =IF(Input!B22="Yes","✅ Has Mortgage (Asset Backing)","ℹ️ No Mortgage Listed") -> ✅ Has Mortgage (Asset Backing)
A22: Loan Purpose | B22: =IF(Input!B16="Auto","✅ Asset-Backed Loan",IF(Input!B16="Home","✅ Secured Loan","⚠️ Unsecured Purpose")) -> ✅ Asset-Backed Loan

Sheet Coefficients
A1: Variables | B1: Coefficients | C1: VariableTypes | D1: Notes
A2: (Intercept) | B2: -1.1114439 | C2: Intercept
A3: Age | B3: -0.039978376 | C3: Numeric
A4: CreditScore | B4: -0.00079600962 | C4: Numeric
A5: MonthsEmployed | B5: -0.0099327384 | C5: Numeric
A6: NumCreditLines | B6: 0.081790138 | C6: Numeric
A7: InterestRate | B7: 0.070657887 | C7: Numeric
A8: LoanTerm | B8: 0.00070293739 | C8: Numeric
A9: DTIRatio | B9: 0.26356391 | C9: Numeric
A10: EducationHigh School | B10: 0.10194407 | C10: Categorical_Dummy | D10: Reference category for Education: Bachelor's
A11: EducationMaster's | B11: -0.10510498 | C11: Categorical_Dummy | D11: Reference category for Education: Bachelor's
A12: EducationPhD | B12: -0.17210521 | C12: Categorical_Dummy | D12: Reference category for Education: Bachelor's
A13: EmploymentTypePart-Time | B13: 0.27361261 | C13: Categorical_Dummy | D13: Reference category for EmploymentType: Full-time
A14: EmploymentTypeSelf-Employed | B14: 0.21158568 | C14: Categorical_Dummy | D14: Reference category for EmploymentType: Full-time
A15: EmploymentTypeUnemployed | B15: 0.43614815 | C15: Categorical_Dummy | D15: Reference category for EmploymentType: Full-time
A16: MaritalStatusMarried | B16: -0.23160429 | C16: Categorical_Dummy | D16: Reference category for MaritalStatus: Divorced
A17: MaritalStatusSingle | B17: -0.060844538 | C17: Categorical_Dummy | D17: Reference category for MaritalStatus: Divorced
A18: HasMortgageYes | B18: -0.16546662 | C18: Categorical_Dummy
A19: HasDependentsYes | B19: -0.24300757 | C19: Categorical_Dummy
A20: LoanPurposeBusiness | B20: 0.04848521 | C20: Categorical_Dummy | D20: Reference category for LoanPurpose: Auto
A21: LoanPurposeEducation | B21: -0.0037945576 | C21: Categorical_Dummy | D21: Reference category for LoanPurpose: Auto
A22: LoanPurposeHome | B22: -0.19313989 | C22: Categorical_Dummy | D22: Reference category for LoanPurpose: Auto
A23: LoanPurposeOther | B23: 0.0069125587 | C23: Categorical_Dummy | D23: Reference category for LoanPurpose: Auto
A24: HasCoSignerYes | B24: -0.26882894 | C24: Categorical_Dummy
A25: LoanToIncome | B25: 0.21339646 | C25: Numeric

Sheet Calculations
A1: Age | B1: =Input!B4 -> 45 | C1: =B1 -> 45 | D1: =IFERROR(VLOOKUP(A1,Coefficients!A:B,2,FALSE),0) -> -0.039978376 | E1: =C1*D1 -> -1.7990269 | G1: Linear Combination | M1: Drop Down List Options (Input Page)
A2: Income | B2: =Input!B5 -> 95000 | C2: =B2 -> 95000 | D2: =IFERROR(VLOOKUP(A2,Coefficients!A:B,2,FALSE),0) -> 0 | E2: =C2*D2 -> 0 | G2: =SUM(E:E) -> -2.7365657 | M2: High School
A3: LoanAmount | B3: =Input!B13 -> 85000 | C3: =B3 -> 85000 | D3: =IFERROR(VLOOKUP(A3,Coefficients!A:B,2,FALSE),0) -> 0 | E3: =C3*D3 -> 0 | M3: Bachelor's
A4: CreditScore | B4: =Input!B19 -> 750 | C4: =B4 -> 750 | D4: =IFERROR(VLOOKUP(A4,Coefficients!A:B,2,FALSE),0) -> -0.00079600962 | E4: =C4*D4 -> -0.59700721 | G4: Default Probability | M4: Master's
A5: MonthsEmployed | B5: =Input!B6 -> 48 | C5: =B5 -> 48 | D5: =IFERROR(VLOOKUP(A5,Coefficients!A:B,2,FALSE),0) -> -0.0099327384 | E5: =C5*D5 -> -0.47677144 | G5: =1/(1+EXP(-G2)) -> 0.060849865 | M5: PhD
A6: NumCreditLines | B6: =Input!B21 -> 6 | C6: =B6 -> 6 | D6: =IFERROR(VLOOKUP(A6,Coefficients!A:B,2,FALSE),0) -> 0.081790138 | E6: =C6*D6 -> 0.49074083 | M6: Unemployed
A7: InterestRate | B7: =Input!B14 -> 15 | C7: =B7 -> 15 | D7: =IFERROR(VLOOKUP(A7,Coefficients!A:B,2,FALSE),0) -> 0.070657887 | E7: =C7*D7 -> 1.0598683 | G7: Default Probability (%) | M7: Part-Time
A8: LoanTerm | B8: =Input!B15 -> 36 | C8: =B8 -> 36 | D8: =IFERROR(VLOOKUP(A8,Coefficients!A:B,2,FALSE),0) -> 0.00070293739 | E8: =C8*D8 -> 0.025305746 | G8: =G5*100 -> 6.0849865 | M8: Full-Time
A9: DTIRatio | B9: =Input!B20 -> 0.6 | C9: =B9 -> 0.6 | D9: =IFERROR(VLOOKUP(A9,Coefficients!A:B,2,FALSE),0) -> 0.26356391 | E9: =C9*D9 -> 0.15813835 | M9: Self-Employed
A10: LoanToIncome | B10: =Input!B13/Input!B5 -> 0.89473684 | C10: =B10 -> 0.89473684 | D10: =IFERROR(VLOOKUP(A10,Coefficients!A:B,2,FALSE),0) -> 0.21339646 | E10: =C10*D10 -> 0.19093367 | G10: Risk Level | M10: Single
A11: (Intercept) | B11: 1 | C11: =B11 -> 1 | D11: =IFERROR(VLOOKUP(A11,Coefficients!A:B,2,FALSE),0) -> -1.1114439 | E11: =C11*D11 -> -1.1114439 | G11: =IF(G8<5,"LOW",IF(G8<15,"MEDIUM",IF(G8<25,"HIGH","VERY HIGH"))) -> MEDIUM | M11: Married
A12: EducationHigh School | B12: =Input!B7 -> Bachelor's | C12: =IF(B12="HighSchool",1,0) -> 0 | D12: =IFERROR(VLOOKUP(A12,Coefficients!A:B,2,FALSE),0) -> 0.10194407 | E12: =C12*D12 -> 0 | M12: Divorced
A13: EducationBachelor's | B13: =Input!B7 -> Bachelor's | C13: =IF(B13="Bachelor's",1,0) -> 1 | D13: =IFERROR(VLOOKUP(A13,Coefficients!A:B,2,FALSE),0) -> 0 | E13: =C13*D13 -> 0 | M13: Yes
A14: EducationMaster's | B14: =Input!B7 -> Bachelor's | C14: =IF(B14="Master's",1,0) -> 0 | D14: =IFERROR(VLOOKUP(A14,Coefficients!A:B,2,FALSE),0) -> -0.10510498 | E14: =C14*D14 -> 0 | M14: No
A15: EducationPhD | B15: =Input!B7 -> Bachelor's | C15: =IF(B15="PhD",1,0) -> 0 | D15: =IFERROR(VLOOKUP(A15,Coefficients!A:B,2,FALSE),0) -> -0.17210521 | E15: =C15*D15 -> 0 | M15: Auto
A16: EmploymentTypeUnemployed | B16: =Input!B8 -> Full-Time | C16: =IF(B16="Unemployed",1,0) -> 0 | D16: =IFERROR(VLOOKUP(A16,Coefficients!A:B,2,FALSE),0) -> 0.43614815 | E16: =C16*D16 -> 0 | M16: 12
A17: EmploymentTypePart-Time | B17: =Input!B8 -> Full-Time | C17: =IF(B17="Part-Time",1,0) -> 0 | D17: =IFERROR(VLOOKUP(A17,Coefficients!A:B,2,FALSE),0) -> 0.27361261 | E17: =C17*D17 -> 0 | M17: 24
A18: EmploymentTypeFull-Time | B18: =Input!B8 -> Full-Time | C18: =IF(B18="Full-Time",1,0) -> 1 | D18: =IFERROR(VLOOKUP(A18,Coefficients!A:B,2,FALSE),0) -> 0 | E18: =C18*D18 -> 0 | M18: 36
A19: EmploymentTypeSelf-Employed | B19: =Input!B8 -> Full-Time | C19: =IF(B19="Self-Employed",1,0) -> 0 | D19: =IFERROR(VLOOKUP(A19,Coefficients!A:B,2,FALSE),0) -> 0.21158568 | E19: =C19*D19 -> 0 | M19: 48
A20: MaritalStatusSingle | B20: =Input!B9 -> Divorced | C20: =IF(B20="Single",1,0) -> 0 | D20: =IFERROR(VLOOKUP(A20,Coefficients!A:B,2,FALSE),0) -> -0.060844538 | E20: =C20*D20 -> 0 | M20: 60
A21: MaritalStatusMarried | B21: =Input!B9 -> Divorced | C21: =IF(B21="Married",1,0) -> 0 | D21: =IFERROR(VLOOKUP(A21,Coefficients!A:B,2,FALSE),0) -> -0.23160429 | E21: =C21*D21 -> 0 | M21: 72
A22: MaritalStatusDivorced | B22: =Input!B9 -> Divorced | C22: =IF(B22="Divorced",1,0) -> 1 | D22: =IFERROR(VLOOKUP(A22,Coefficients!A:B,2,FALSE),0) -> 0 | E22: =C22*D22 -> 0 | M22: 84
A23: HasMortgageYes | B23: =Input!B22 -> Yes | C23: =IF(B23="Yes",1,0) -> 1 | D23: =IFERROR(VLOOKUP(A23,Coefficients!A:B,2,FALSE),0) -> -0.16546662 | E23: =C23*D23 -> -0.16546662
A24: HasDependentsYes | B24: =Input!B10 -> Yes | C24: =IF(B24="Yes",1,0) -> 1 | D24: =IFERROR(VLOOKUP(A24,Coefficients!A:B,2,FALSE),0) -> -0.24300757 | E24: =C24*D24 -> -0.24300757
A25: HasCoSignerYes | B25: =Input!B23 -> Yes | C25: =IF(B25="Yes",1,0) -> 1 | D25: =IFERROR(VLOOKUP(A25,Coefficients!A:B,2,FALSE),0) -> -0.26882894 | E25: =C25*D25 -> -0.26882894
A26: LoanPurposeOther | B26: =Input!B16 -> Auto | C26: =IF(B26="Other",1,0) -> 0 | D26: =IFERROR(VLOOKUP(A26,Coefficients!A:B,2,FALSE),0) -> 0.0069125587 | E26: =C26*D26 -> 0
A27: LoanPurposeAuto | B27: =Input!B16 -> Auto | C27: =IF(B27="Auto",1,0) -> 1 | D27: =IFERROR(VLOOKUP(A27,Coefficients!A:B,2,FALSE),0) -> 0 | E27: =C27*D27 -> 0
A28: LoanPurposeEducation | B28: =Input!B16 -> Auto | C28: =IF(B28="Education",1,0) -> 0 | D28: =IFERROR(VLOOKUP(A28,Coefficients!A:B,2,FALSE),0) -> -0.0037945576 | E28: =C28*D28 -> 0
A29: LoanPurposeHome | B29: =Input!B16 -> Auto | C29: =IF(B29="Home",1,0) -> 0 | D29: =IFERROR(VLOOKUP(A29,Coefficients!A:B,2,FALSE),0) -> -0.19313989 | E29: =C29*D29 -> 0
A30: LoanPurposeBusiness | B30: =Input!B16 -> Auto | C30: =IF(B30="Business",1,0) -> 0 | D30: =IFERROR(VLOOKUP(A30,Coefficients!A:B,2,FALSE),0) -> 0.04848521 | E30: =C30*D30 -> 0
